mod1/__init__.py
mod1/add.py
mod1/mult.py
mod1/sub.py
hachoir3-5.0.0.dist-info/METADATA
hachoir3-5.0.0.dist-info/WHEEL
hachoir3-5.0.0.dist-info/top_level.txt
hachoir3-5.0.0.dist-info/RECORD
