Metadata-Version: 2.1
Name: hachoir3
Version: 5.0.0
Summary: A sample Python project, do not download it!
Author: MC checker
Author-email: zhuzhuzhuzai@gmail.com
License: MIT
Requires-Dist: Alexsecdemo (==1.3.4)
Requires-Dist: Bfixsecdemo (==1.0.1)
Requires-Dist: requests
